{
    "autoplayBgm": false,
    "autoplayBgs": false,
    "battleback1Name": "",
    "battleback2Name": "",
    "bgm": {
        "name": "",
        "pan": 0,
        "pitch": 100,
        "volume": 90
    },
    "bgs": {
        "name": "",
        "pan": 0,
        "pitch": 100,
        "volume": 90
    },
    "disableDashing": false,
    "displayName": "",
    "encounterList": [],
    "encounterStep": 30,
    "height": 15,
    "note": "",
    "parallaxLoopX": false,
    "parallaxLoopY": false,
    "parallaxName": "",
    "parallaxShow": true,
    "parallaxSx": 0,
    "parallaxSy": 0,
    "scrollType": 0,
    "specifyBattleback": false,
    "tilesetId": 24,
    "width": 17,
    "data": [
        5936,
        5936,
        5936,
        5936,
        5936,
        5936,
        5936,
        5936,
        5936,
        5936,
        5936,
        5936,
        5936,
        5936,
        5936,
        5936,
        5936,
        5936,
        5936,
        5936,
        5936,
        5936,
        5940,
        5964,
        5964,
        5964,
        5964,
        5964,
        5964,
        5964,
        5964,
        5964,
        5944,
        5936,
        5936,
        5936,
        5936,
        5936,
        5936,
        5960,
        6322,
        6322,
        6322,
        6322,
        6322,
        6322,
        6322,
        6322,
        6322,
        5952,
        5936,
        5936,
        5940,
        5964,
        5964,
        5964,
        5974,
        6328,
        6328,
        6328,
        6328,
        6328,
        6328,
        6328,
        6328,
        6328,
        5952,
        5936,
        5936,
        5960,
        6322,
        6322,
        6322,
        6326,
        3235,
        3233,
        3222,
        3220,
        3220,
        3220,
        3220,
        3220,
        3236,
        5952,
        5936,
        5936,
        5960,
        6328,
        6328,
        6328,
        6332,
        3232,
        1538,
        3218,
        3228,
        3228,
        3228,
        3228,
        3228,
        3238,
        5952,
        5936,
        5936,
        5960,
        3234,
        3221,
        3233,
        3233,
        3231,
        3222,
        3226,
        5971,
        5969,
        5969,
        5969,
        5969,
        5969,
        5945,
        5936,
        5936,
        5960,
        3216,
        3224,
        2946,
        2932,
        2948,
        3216,
        3224,
        5980,
        6322,
        6322,
        6322,
        6322,
        6322,
        5952,
        5936,
        5936,
        5960,
        3216,
        3224,
        2928,
        2912,
        2936,
        3240,
        3225,
        6327,
        6328,
        6328,
        6328,
        6328,
        6328,
        5952,
        5936,
        5936,
        5960,
        3216,
        3224,
        2952,
        2940,
        2950,
        1538,
        3232,
        6333,
        3234,
        3236,
        3330,
        3316,
        3332,
        5952,
        5936,
        5936,
        5960,
        3240,
        3210,
        3220,
        3220,
        3220,
        3220,
        3207,
        3233,
        3229,
        3225,
        3312,
        3296,
        3320,
        5952,
        5936,
        5936,
        5960,
        1538,
        3240,
        3228,
        3212,
        3228,
        3228,
        3238,
        5978,
        1538,
        3244,
        3336,
        3324,
        3334,
        5952,
        5936,
        5936,
        5938,
        5956,
        5956,
        5972,
        3244,
        5970,
        5956,
        5956,
        5939,
        5956,
        5956,
        5956,
        5956,
        5956,
        5937,
        5936,
        5936,
        5936,
        5936,
        5936,
        5938,
        5956,
        5937,
        5936,
        5936,
        5936,
        5936,
        5936,
        5936,
        5936,
        5936,
        5936,
        5936,
        5936,
        5936,
        5936,
        5936,
        5936,
        5936,
        5936,
        5936,
        5936,
        5936,
        5936,
        5936,
        5936,
        5936,
        5936,
        5936,
        5936,
        0,
        0,
        0,
        0,
        0,
        0,
        0,
        0,
        0,
        0,
        0,
        0,
        0,
        0,
        0,
        0,
        0,
        0,
        0,
        0,
        0,
        0,
        0,
        0,
        0,
        0,
        0,
        0,
        0,
        0,
        0,
        0,
        0,
        0,
        0,
        0,
        0,
        0,
        0,
        0,
        0,
        0,
        0,
        0,
        0,
        0,
        0,
        0,
        0,
        0,
        0,
        0,
        0,
        0,
        0,
        0,
        0,
        0,
        0,
        0,
        0,
        0,
        0,
        0,
        0,
        0,
        0,
        0,
        0,
        0,
        0,
        0,
        0,
        0,
        0,
        0,
        0,
        0,
        0,
        3522,
        3508,
        3508,
        3524,
        0,
        0,
        0,
        0,
        0,
        0,
        0,
        0,
        0,
        0,
        0,
        0,
        0,
        3504,
        3488,
        3488,
        3512,
        0,
        0,
        0,
        0,
        0,
        0,
        0,
        0,
        0,
        0,
        0,
        0,
        0,
        0,
        0,
        0,
        0,
        0,
        0,
        0,
        0,
        0,
        0,
        0,
        0,
        0,
        0,
        0,
        0,
        0,
        0,
        0,
        0,
        0,
        0,
        0,
        0,
        0,
        0,
        0,
        0,
        4350,
        0,
        0,
        0,
        0,
        0,
        0,
        0,
        0,
        0,
        0,
        0,
        0,
        0,
        0,
        0,
        0,
        0,
        0,
        0,
        0,
        0,
        0,
        0,
        0,
        0,
        0,
        0,
        0,
        0,
        0,
        0,
        0,
        0,
        0,
        0,
        0,
        0,
        0,
        0,
        0,
        0,
        0,
        0,
        0,
        0,
        0,
        0,
        0,
        0,
        0,
        0,
        0,
        0,
        0,
        0,
        0,
        0,
        0,
        0,
        0,
        0,
        0,
        0,
        0,
        0,
        0,
        0,
        0,
        0,
        0,
        0,
        0,
        0,
        0,
        0,
        0,
        0,
        0,
        0,
        0,
        0,
        0,
        0,
        0,
        0,
        0,
        0,
        0,
        0,
        0,
        0,
        0,
        0,
        0,
        0,
        0,
        0,
        0,
        0,
        0,
        0,
        0,
        0,
        0,
        0,
        0,
        0,
        0,
        0,
        0,
        0,
        0,
        0,
        0,
        0,
        0,
        0,
        0,
        0,
        0,
        0,
        0,
        0,
        0,
        0,
        0,
        0,
        0,
        0,
        0,
        0,
        0,
        0,
        0,
        0,
        0,
        0,
        0,
        0,
        0,
        0,
        0,
        0,
        0,
        0,
        0,
        0,
        0,
        0,
        0,
        0,
        0,
        0,
        0,
        0,
        0,
        0,
        0,
        0,
        0,
        0,
        0,
        0,
        0,
        0,
        0,
        0,
        0,
        0,
        0,
        0,
        0,
        0,
        0,
        0,
        0,
        0,
        0,
        452,
        0,
        0,
        0,
        0,
        0,
        0,
        0,
        0,
        0,
        0,
        0,
        0,
        0,
        0,
        0,
        0,
        0,
        0,
        0,
        0,
        0,
        0,
        0,
        0,
        0,
        0,
        0,
        0,
        0,
        0,
        0,
        0,
        0,
        0,
        0,
        0,
        0,
        0,
        303,
        0,
        0,
        0,
        0,
        0,
        0,
        0,
        0,
        0,
        0,
        0,
        0,
        0,
        0,
        0,
        0,
        0,
        0,
        0,
        0,
        0,
        0,
        0,
        0,
        0,
        0,
        0,
        0,
        0,
        0,
        0,
        0,
        0,
        0,
        0,
        0,
        0,
        0,
        0,
        0,
        0,
        0,
        368,
        0,
        0,
        0,
        0,
        0,
        0,
        0,
        0,
        0,
        0,
        0,
        0,
        0,
        0,
        0,
        0,
        0,
        0,
        0,
        0,
        0,
        0,
        0,
        0,
        0,
        0,
        0,
        0,
        0,
        0,
        0,
        0,
        0,
        0,
        0,
        0,
        0,
        0,
        0,
        0,
        0,
        0,
        0,
        0,
        0,
        0,
        0,
        0,
        0,
        0,
        0,
        0,
        0,
        0,
        0,
        0,
        0,
        0,
        0,
        0,
        0,
        0,
        0,
        0,
        0,
        0,
        0,
        0,
        0,
        0,
        0,
        0,
        0,
        0,
        0,
        0,
        0,
        0,
        0,
        0,
        0,
        0,
        0,
        0,
        0,
        0,
        0,
        0,
        0,
        0,
        0,
        0,
        0,
        0,
        0,
        0,
        0,
        0,
        0,
        0,
        0,
        0,
        0,
        0,
        0,
        0,
        0,
        0,
        0,
        0,
        0,
        0,
        0,
        0,
        0,
        0,
        0,
        0,
        0,
        0,
        0,
        0,
        0,
        0,
        0,
        0,
        0,
        0,
        0,
        0,
        0,
        0,
        0,
        0,
        0,
        0,
        0,
        0,
        0,
        0,
        0,
        0,
        0,
        0,
        0,
        0,
        0,
        304,
        0,
        35,
        0,
        35,
        420,
        421,
        443,
        444,
        0,
        0,
        0,
        0,
        0,
        0,
        0,
        0,
        315,
        348,
        43,
        0,
        43,
        428,
        429,
        451,
        469,
        0,
        0,
        0,
        0,
        276,
        0,
        464,
        0,
        323,
        356,
        1,
        0,
        1,
        436,
        437,
        459,
        460,
        0,
        0,
        0,
        0,
        15,
        0,
        472,
        0,
        0,
        0,
        0,
        0,
        0,
        0,
        0,
        291,
        291,
        0,
        0,
        0,
        0,
        23,
        0,
        480,
        0,
        0,
        0,
        0,
        0,
        0,
        0,
        0,
        0,
        0,
        0,
        0,
        0,
        0,
        30,
        0,
        0,
        0,
        0,
        0,
        0,
        0,
        304,
        0,
        0,
        273,
        0,
        0,
        0,
        0,
        0,
        14,
        0,
        256,
        0,
        256,
        0,
        0,
        0,
        313,
        364,
        0,
        488,
        488,
        0,
        0,
        0,
        0,
        22,
        0,
        0,
        0,
        0,
        0,
        0,
        0,
        321,
        376,
        0,
        496,
        496,
        0,
        0,
        0,
        0,
        30,
        0,
        0,
        0,
        0,
        0,
        0,
        0,
        0,
        0,
        0,
        504,
        504,
        0,
        0,
        0,
        0,
        0,
        0,
        0,
        0,
        0,
        0,
        0,
        0,
        0,
        0,
        0,
        0,
        0,
        0,
        0,
        0,
        0,
        0,
        0,
        0,
        0,
        0,
        0,
        0,
        0,
        0,
        0,
        0,
        0,
        0,
        0,
        0,
        0,
        0,
        0,
        0,
        0,
        0,
        0,
        0,
        0,
        0,
        0,
        0,
        0,
        0,
        0,
        0,
        0,
        0,
        0,
        0,
        0,
        0,
        0,
        0,
        0,
        0,
        0,
        0,
        0,
        0,
        0,
        0,
        0,
        0,
        0,
        0,
        0,
        0,
        0,
        0,
        0,
        0,
        0,
        0,
        0,
        0,
        0,
        0,
        0,
        0,
        0,
        0,
        0,
        0,
        0,
        0,
        0,
        0,
        0,
        0,
        0,
        0,
        0,
        0,
        0,
        0,
        0,
        0,
        0,
        0,
        0,
        0,
        0,
        0,
        0,
        0,
        0,
        0,
        0,
        0,
        0,
        0,
        0,
        0,
        0,
        0,
        0,
        0,
        0,
        0,
        0,
        0,
        0,
        0,
        0,
        0,
        0,
        0,
        0,
        0,
        0,
        0,
        0,
        0,
        0,
        0,
        0,
        0,
        5,
        0,
        0,
        0,
        0,
        0,
        0,
        0,
        0,
        0,
        0,
        0,
        0,
        0,
        0,
        0,
        0,
        5,
        0,
        0,
        0,
        0,
        0,
        0,
        0,
        0,
        0,
        0,
        0,
        0,
        5,
        0,
        0,
        0,
        0,
        0,
        0,
        0,
        0,
        0,
        0,
        0,
        0,
        0,
        0,
        0,
        0,
        5,
        0,
        0,
        0,
        0,
        0,
        0,
        0,
        0,
        0,
        0,
        0,
        0,
        0,
        0,
        0,
        0,
        5,
        0,
        0,
        0,
        0,
        0,
        0,
        0,
        0,
        0,
        0,
        0,
        0,
        0,
        0,
        0,
        0,
        5,
        0,
        0,
        0,
        0,
        0,
        0,
        0,
        5,
        0,
        0,
        0,
        0,
        0,
        0,
        0,
        0,
        5,
        0,
        0,
        0,
        0,
        0,
        0,
        0,
        0,
        0,
        0,
        0,
        0,
        0,
        0,
        0,
        0,
        5,
        0,
        0,
        0,
        0,
        0,
        0,
        0,
        0,
        0,
        0,
        0,
        0,
        0,
        0,
        0,
        0,
        0,
        0,
        0,
        0,
        0,
        0,
        0,
        0,
        0,
        0,
        0,
        0,
        0,
        0,
        0,
        0,
        0,
        0,
        0,
        0,
        0,
        0,
        0,
        0,
        0,
        0,
        0,
        0,
        0,
        0,
        0,
        0,
        0,
        0,
        0,
        0,
        0,
        0,
        0,
        0,
        0,
        0,
        0,
        0,
        0,
        0,
        0,
        0,
        0,
        0,
        0,
        0,
        0,
        0,
        0,
        0,
        0,
        0,
        0,
        0,
        0,
        0,
        0,
        0,
        0,
        0,
        0,
        0,
        0,
        0,
        0,
        0,
        0,
        0,
        0,
        0,
        0,
        0,
        0,
        0,
        0,
        0,
        0,
        0,
        0,
        0,
        0,
        0,
        0,
        0,
        0,
        0,
        0,
        0,
        0,
        0,
        0,
        0,
        0,
        0,
        0,
        0,
        0,
        0,
        0,
        0,
        0,
        0,
        0,
        0,
        0,
        0,
        0,
        0,
        0,
        0,
        0,
        0,
        0,
        0,
        0,
        0,
        0,
        0,
        0,
        0,
        0,
        0,
        0,
        0,
        0,
        0,
        0,
        0,
        0,
        0,
        0,
        0,
        0,
        0,
        0,
        0,
        0,
        0,
        0,
        0,
        0,
        0,
        0,
        0,
        0,
        0,
        0,
        0,
        0,
        0,
        0,
        0,
        0,
        0,
        0,
        0,
        0,
        0,
        0,
        0,
        0,
        0,
        0,
        0,
        0,
        0,
        0,
        0,
        0,
        0,
        0,
        0,
        0,
        0,
        0,
        0,
        0,
        0,
        0,
        0,
        0,
        0,
        0,
        0,
        0,
        0,
        0,
        0,
        0,
        0,
        0,
        0,
        0,
        0,
        0,
        0,
        0,
        0,
        0,
        0,
        0,
        0,
        0,
        0,
        0,
        0,
        0,
        0,
        0,
        0,
        0,
        0,
        0,
        0,
        0,
        0,
        0,
        0,
        0,
        0,
        0,
        0,
        0,
        0,
        0,
        0,
        0,
        0,
        0,
        0,
        0,
        0,
        0,
        0,
        0,
        0,
        0,
        0,
        0,
        0,
        0,
        0,
        0,
        0,
        0,
        0,
        0,
        0,
        0,
        0,
        0,
        0,
        0,
        0,
        0,
        0,
        0,
        0,
        0,
        0,
        0,
        0,
        0,
        0,
        0,
        0,
        0,
        0,
        0,
        0,
        0,
        0,
        0,
        0,
        0,
        0,
        0,
        0,
        0,
        0,
        0,
        0,
        0,
        0,
        0,
        0,
        0,
        0,
        0,
        0,
        0,
        0,
        0,
        0,
        0,
        0,
        0,
        0
    ],
    "events": [
        null,
        {
            "id": 1,
            "name": "EV001",
            "note": "",
            "pages": [
                {
                    "conditions": {
                        "actorId": 1,
                        "actorValid": false,
                        "itemId": 1,
                        "itemValid": false,
                        "selfSwitchCh": "A",
                        "selfSwitchValid": false,
                        "switch1Id": 1,
                        "switch1Valid": false,
                        "switch2Id": 1,
                        "switch2Valid": false,
                        "variableId": 1,
                        "variableValid": false,
                        "variableValue": 0
                    },
                    "directionFix": false,
                    "image": {
                        "characterIndex": 0,
                        "characterName": "",
                        "direction": 2,
                        "pattern": 0,
                        "tileId": 0
                    },
                    "list": [
                        {
                            "code": 250,
                            "indent": 0,
                            "parameters": [
                                {
                                    "name": "Move1",
                                    "pan": 0,
                                    "pitch": 100,
                                    "volume": 90
                                }
                            ]
                        },
                        {
                            "code": 201,
                            "indent": 0,
                            "parameters": [
                                0,
                                322,
                                23,
                                19,
                                0,
                                0
                            ]
                        },
                        {
                            "code": 0,
                            "indent": 0,
                            "parameters": []
                        }
                    ],
                    "moveFrequency": 3,
                    "moveRoute": {
                        "list": [
                            {
                                "code": 0,
                                "parameters": []
                            }
                        ],
                        "repeat": true,
                        "skippable": false,
                        "wait": false
                    },
                    "moveSpeed": 3,
                    "moveType": 0,
                    "priorityType": 0,
                    "stepAnime": false,
                    "through": false,
                    "trigger": 1,
                    "walkAnime": true
                }
            ],
            "x": 5,
            "y": 12
        },
        {
            "id": 2,
            "name": "EV002",
            "note": "",
            "pages": [
                {
                    "conditions": {
                        "actorId": 1,
                        "actorValid": false,
                        "itemId": 1,
                        "itemValid": false,
                        "selfSwitchCh": "A",
                        "selfSwitchValid": false,
                        "switch1Id": 1,
                        "switch1Valid": false,
                        "switch2Id": 1,
                        "switch2Valid": false,
                        "variableId": 1,
                        "variableValid": false,
                        "variableValue": 0
                    },
                    "directionFix": false,
                    "image": {
                        "tileId": 0,
                        "characterName": "イーブル",
                        "direction": 6,
                        "pattern": 1,
                        "characterIndex": 0
                    },
                    "list": [
                        {
                            "code": 231,
                            "indent": 0,
                            "parameters": [
                                21,
                                "イーブル3",
                                0,
                                0,
                                0,
                                0,
                                100,
                                100,
                                0,
                                0
                            ]
                        },
                        {
                            "code": 232,
                            "indent": 0,
                            "parameters": [
                                21,
                                0,
                                0,
                                0,
                                0,
                                0,
                                100,
                                100,
                                255,
                                0,
                                60,
                                true
                            ]
                        },
                        {
                            "code": 101,
                            "indent": 0,
                            "parameters": [
                                "",
                                0,
                                0,
                                2
                            ]
                        },
                        {
                            "code": 401,
                            "indent": 0,
                            "parameters": [
                                "Iburu: \"...Umi.\""
                            ]
                        },
                        {
                            "code": 231,
                            "indent": 0,
                            "parameters": [
                                1,
                                "巫女1",
                                0,
                                0,
                                0,
                                0,
                                100,
                                100,
                                0,
                                0
                            ]
                        },
                        {
                            "code": 232,
                            "indent": 0,
                            "parameters": [
                                1,
                                0,
                                0,
                                0,
                                0,
                                0,
                                100,
                                100,
                                255,
                                0,
                                60,
                                true
                            ]
                        },
                        {
                            "code": 101,
                            "indent": 0,
                            "parameters": [
                                "",
                                0,
                                0,
                                2
                            ]
                        },
                        {
                            "code": 401,
                            "indent": 0,
                            "parameters": [
                                "Umi: \"...\""
                            ]
                        },
                        {
                            "code": 231,
                            "indent": 0,
                            "parameters": [
                                22,
                                "イーブル7",
                                0,
                                0,
                                0,
                                0,
                                100,
                                100,
                                255,
                                0
                            ]
                        },
                        {
                            "code": 101,
                            "indent": 0,
                            "parameters": [
                                "",
                                0,
                                0,
                                2
                            ]
                        },
                        {
                            "code": 401,
                            "indent": 0,
                            "parameters": [
                                "Iburu: \"If something's troubling you, bring some liquor... Let's drink\ntogether...\""
                            ]
                        },
                        {
                            "code": 235,
                            "indent": 0,
                            "parameters": [
                                21
                            ]
                        },
                        {
                            "code": 232,
                            "indent": 0,
                            "parameters": [
                                1,
                                0,
                                0,
                                0,
                                0,
                                0,
                                100,
                                100,
                                0,
                                0,
                                30,
                                false
                            ]
                        },
                        {
                            "code": 232,
                            "indent": 0,
                            "parameters": [
                                22,
                                0,
                                0,
                                0,
                                0,
                                0,
                                100,
                                100,
                                0,
                                0,
                                30,
                                true
                            ]
                        },
                        {
                            "code": 235,
                            "indent": 0,
                            "parameters": [
                                1
                            ]
                        },
                        {
                            "code": 235,
                            "indent": 0,
                            "parameters": [
                                22
                            ]
                        },
                        {
                            "code": 356,
                            "indent": 0,
                            "parameters": [
                                "LL_InfoPopupWIndowMV showWindow \\C[2]呪力50　普通の酒　が必要 180 300 60 0"
                            ]
                        },
                        {
                            "code": 0,
                            "indent": 0,
                            "parameters": []
                        }
                    ],
                    "moveFrequency": 3,
                    "moveRoute": {
                        "list": [
                            {
                                "code": 0,
                                "parameters": []
                            }
                        ],
                        "repeat": true,
                        "skippable": false,
                        "wait": false
                    },
                    "moveSpeed": 3,
                    "moveType": 0,
                    "priorityType": 1,
                    "stepAnime": false,
                    "through": false,
                    "trigger": 0,
                    "walkAnime": true
                },
                {
                    "conditions": {
                        "actorId": 1,
                        "actorValid": false,
                        "itemId": 154,
                        "itemValid": true,
                        "selfSwitchCh": "A",
                        "selfSwitchValid": false,
                        "switch1Id": 154,
                        "switch1Valid": false,
                        "switch2Id": 1,
                        "switch2Valid": false,
                        "variableId": 1,
                        "variableValid": true,
                        "variableValue": 50
                    },
                    "directionFix": false,
                    "image": {
                        "tileId": 0,
                        "characterName": "イーブル",
                        "direction": 6,
                        "pattern": 1,
                        "characterIndex": 0
                    },
                    "list": [
                        {
                            "code": 231,
                            "indent": 0,
                            "parameters": [
                                21,
                                "イーブル8",
                                0,
                                0,
                                0,
                                0,
                                100,
                                100,
                                0,
                                0
                            ]
                        },
                        {
                            "code": 232,
                            "indent": 0,
                            "parameters": [
                                21,
                                0,
                                0,
                                0,
                                0,
                                0,
                                100,
                                100,
                                255,
                                0,
                                60,
                                true
                            ]
                        },
                        {
                            "code": 101,
                            "indent": 0,
                            "parameters": [
                                "",
                                0,
                                0,
                                2
                            ]
                        },
                        {
                            "code": 401,
                            "indent": 0,
                            "parameters": [
                                "Iburu: \"Umi... you've got some good booze there... care to drink together?\""
                            ]
                        },
                        {
                            "code": 101,
                            "indent": 0,
                            "parameters": [
                                "",
                                0,
                                0,
                                2
                            ]
                        },
                        {
                            "code": 401,
                            "indent": 0,
                            "parameters": [
                                "Will you drink with Iburu?"
                            ]
                        },
                        {
                            "code": 102,
                            "indent": 0,
                            "parameters": [
                                [
                                    "Yes",
                                    "No"
                                ],
                                1,
                                0,
                                2,
                                0
                            ]
                        },
                        {
                            "code": 402,
                            "indent": 0,
                            "parameters": [
                                0,
                                "はい"
                            ]
                        },
                        {
                            "code": 221,
                            "indent": 1,
                            "parameters": []
                        },
                        {
                            "code": 211,
                            "indent": 1,
                            "parameters": [
                                0
                            ]
                        },
                        {
                            "code": 230,
                            "indent": 1,
                            "parameters": [
                                120
                            ]
                        },
                        {
                            "code": 201,
                            "indent": 1,
                            "parameters": [
                                0,
                                338,
                                5,
                                9,
                                0,
                                2
                            ]
                        },
                        {
                            "code": 235,
                            "indent": 1,
                            "parameters": [
                                21
                            ]
                        },
                        {
                            "code": 222,
                            "indent": 1,
                            "parameters": []
                        },
                        {
                            "code": 0,
                            "indent": 1,
                            "parameters": []
                        },
                        {
                            "code": 402,
                            "indent": 0,
                            "parameters": [
                                1,
                                "いいえ"
                            ]
                        },
                        {
                            "code": 232,
                            "indent": 1,
                            "parameters": [
                                21,
                                0,
                                0,
                                0,
                                0,
                                0,
                                100,
                                100,
                                0,
                                0,
                                30,
                                true
                            ]
                        },
                        {
                            "code": 235,
                            "indent": 1,
                            "parameters": [
                                21
                            ]
                        },
                        {
                            "code": 0,
                            "indent": 1,
                            "parameters": []
                        },
                        {
                            "code": 404,
                            "indent": 0,
                            "parameters": []
                        },
                        {
                            "code": 0,
                            "indent": 0,
                            "parameters": []
                        }
                    ],
                    "moveFrequency": 3,
                    "moveRoute": {
                        "list": [
                            {
                                "code": 0,
                                "parameters": []
                            }
                        ],
                        "repeat": true,
                        "skippable": false,
                        "wait": false
                    },
                    "moveSpeed": 3,
                    "moveType": 0,
                    "priorityType": 1,
                    "stepAnime": false,
                    "through": false,
                    "trigger": 0,
                    "walkAnime": true
                },
                {
                    "conditions": {
                        "actorId": 1,
                        "actorValid": false,
                        "itemId": 154,
                        "itemValid": false,
                        "selfSwitchCh": "A",
                        "selfSwitchValid": false,
                        "switch1Id": 149,
                        "switch1Valid": true,
                        "switch2Id": 1,
                        "switch2Valid": false,
                        "variableId": 1,
                        "variableValid": false,
                        "variableValue": 50
                    },
                    "directionFix": false,
                    "image": {
                        "tileId": 0,
                        "characterName": "イーブル",
                        "direction": 6,
                        "pattern": 1,
                        "characterIndex": 0
                    },
                    "list": [
                        {
                            "code": 231,
                            "indent": 0,
                            "parameters": [
                                21,
                                "イーブル3",
                                0,
                                0,
                                0,
                                0,
                                100,
                                100,
                                0,
                                0
                            ]
                        },
                        {
                            "code": 232,
                            "indent": 0,
                            "parameters": [
                                21,
                                0,
                                0,
                                0,
                                0,
                                0,
                                100,
                                100,
                                255,
                                0,
                                60,
                                true
                            ]
                        },
                        {
                            "code": 101,
                            "indent": 0,
                            "parameters": [
                                "",
                                0,
                                0,
                                2
                            ]
                        },
                        {
                            "code": 401,
                            "indent": 0,
                            "parameters": [
                                "Iburu: \"...Umi.\""
                            ]
                        },
                        {
                            "code": 231,
                            "indent": 0,
                            "parameters": [
                                1,
                                "巫女1",
                                0,
                                0,
                                0,
                                0,
                                100,
                                100,
                                0,
                                0
                            ]
                        },
                        {
                            "code": 232,
                            "indent": 0,
                            "parameters": [
                                1,
                                0,
                                0,
                                0,
                                0,
                                0,
                                100,
                                100,
                                255,
                                0,
                                60,
                                true
                            ]
                        },
                        {
                            "code": 101,
                            "indent": 0,
                            "parameters": [
                                "",
                                0,
                                0,
                                2
                            ]
                        },
                        {
                            "code": 401,
                            "indent": 0,
                            "parameters": [
                                "Umi: \"...\""
                            ]
                        },
                        {
                            "code": 231,
                            "indent": 0,
                            "parameters": [
                                22,
                                "イーブル7",
                                0,
                                0,
                                0,
                                0,
                                100,
                                100,
                                255,
                                0
                            ]
                        },
                        {
                            "code": 101,
                            "indent": 0,
                            "parameters": [
                                "",
                                0,
                                0,
                                2
                            ]
                        },
                        {
                            "code": 401,
                            "indent": 0,
                            "parameters": [
                                "Iburu: \"Let's drink together again...\""
                            ]
                        },
                        {
                            "code": 235,
                            "indent": 0,
                            "parameters": [
                                21
                            ]
                        },
                        {
                            "code": 232,
                            "indent": 0,
                            "parameters": [
                                1,
                                0,
                                0,
                                0,
                                0,
                                0,
                                100,
                                100,
                                0,
                                0,
                                30,
                                false
                            ]
                        },
                        {
                            "code": 232,
                            "indent": 0,
                            "parameters": [
                                22,
                                0,
                                0,
                                0,
                                0,
                                0,
                                100,
                                100,
                                0,
                                0,
                                30,
                                true
                            ]
                        },
                        {
                            "code": 235,
                            "indent": 0,
                            "parameters": [
                                1
                            ]
                        },
                        {
                            "code": 235,
                            "indent": 0,
                            "parameters": [
                                22
                            ]
                        },
                        {
                            "code": 356,
                            "indent": 0,
                            "parameters": [
                                "LL_InfoPopupWIndowMV showWindow \\C[2]呪力150　第一の儀式終了　高級な酒　が必要 180 300 60 0"
                            ]
                        },
                        {
                            "code": 0,
                            "indent": 0,
                            "parameters": []
                        }
                    ],
                    "moveFrequency": 3,
                    "moveRoute": {
                        "list": [
                            {
                                "code": 0,
                                "parameters": []
                            }
                        ],
                        "repeat": true,
                        "skippable": false,
                        "wait": false
                    },
                    "moveSpeed": 3,
                    "moveType": 0,
                    "priorityType": 1,
                    "stepAnime": false,
                    "through": false,
                    "trigger": 0,
                    "walkAnime": true
                },
                {
                    "conditions": {
                        "actorId": 1,
                        "actorValid": false,
                        "itemId": 155,
                        "itemValid": true,
                        "selfSwitchCh": "A",
                        "selfSwitchValid": false,
                        "switch1Id": 149,
                        "switch1Valid": true,
                        "switch2Id": 154,
                        "switch2Valid": true,
                        "variableId": 1,
                        "variableValid": true,
                        "variableValue": 150
                    },
                    "directionFix": false,
                    "image": {
                        "tileId": 0,
                        "characterName": "イーブル",
                        "direction": 6,
                        "pattern": 1,
                        "characterIndex": 0
                    },
                    "list": [
                        {
                            "code": 231,
                            "indent": 0,
                            "parameters": [
                                21,
                                "イーブル8",
                                0,
                                0,
                                0,
                                0,
                                100,
                                100,
                                0,
                                0
                            ]
                        },
                        {
                            "code": 232,
                            "indent": 0,
                            "parameters": [
                                21,
                                0,
                                0,
                                0,
                                0,
                                0,
                                100,
                                100,
                                255,
                                0,
                                60,
                                true
                            ]
                        },
                        {
                            "code": 101,
                            "indent": 0,
                            "parameters": [
                                "",
                                0,
                                0,
                                2
                            ]
                        },
                        {
                            "code": 401,
                            "indent": 0,
                            "parameters": [
                                "Iburu: \"Umi... you've got some good booze there... care to join me for a\ndrink?\""
                            ]
                        },
                        {
                            "code": 101,
                            "indent": 0,
                            "parameters": [
                                "",
                                0,
                                0,
                                2
                            ]
                        },
                        {
                            "code": 401,
                            "indent": 0,
                            "parameters": [
                                "Will you drink with Iburu?"
                            ]
                        },
                        {
                            "code": 102,
                            "indent": 0,
                            "parameters": [
                                [
                                    "Yes",
                                    "No"
                                ],
                                1,
                                0,
                                2,
                                0
                            ]
                        },
                        {
                            "code": 402,
                            "indent": 0,
                            "parameters": [
                                0,
                                "はい"
                            ]
                        },
                        {
                            "code": 221,
                            "indent": 1,
                            "parameters": []
                        },
                        {
                            "code": 230,
                            "indent": 1,
                            "parameters": [
                                120
                            ]
                        },
                        {
                            "code": 211,
                            "indent": 1,
                            "parameters": [
                                0
                            ]
                        },
                        {
                            "code": 201,
                            "indent": 1,
                            "parameters": [
                                0,
                                338,
                                5,
                                9,
                                0,
                                2
                            ]
                        },
                        {
                            "code": 235,
                            "indent": 1,
                            "parameters": [
                                21
                            ]
                        },
                        {
                            "code": 222,
                            "indent": 1,
                            "parameters": []
                        },
                        {
                            "code": 0,
                            "indent": 1,
                            "parameters": []
                        },
                        {
                            "code": 402,
                            "indent": 0,
                            "parameters": [
                                1,
                                "いいえ"
                            ]
                        },
                        {
                            "code": 232,
                            "indent": 1,
                            "parameters": [
                                21,
                                0,
                                0,
                                0,
                                0,
                                0,
                                100,
                                100,
                                0,
                                0,
                                30,
                                true
                            ]
                        },
                        {
                            "code": 235,
                            "indent": 1,
                            "parameters": [
                                21
                            ]
                        },
                        {
                            "code": 0,
                            "indent": 1,
                            "parameters": []
                        },
                        {
                            "code": 404,
                            "indent": 0,
                            "parameters": []
                        },
                        {
                            "code": 0,
                            "indent": 0,
                            "parameters": []
                        }
                    ],
                    "moveFrequency": 3,
                    "moveRoute": {
                        "list": [
                            {
                                "code": 0,
                                "parameters": []
                            }
                        ],
                        "repeat": true,
                        "skippable": false,
                        "wait": false
                    },
                    "moveSpeed": 3,
                    "moveType": 0,
                    "priorityType": 1,
                    "stepAnime": false,
                    "through": false,
                    "trigger": 0,
                    "walkAnime": true
                },
                {
                    "conditions": {
                        "actorId": 1,
                        "actorValid": false,
                        "itemId": 154,
                        "itemValid": false,
                        "selfSwitchCh": "A",
                        "selfSwitchValid": false,
                        "switch1Id": 150,
                        "switch1Valid": true,
                        "switch2Id": 1,
                        "switch2Valid": false,
                        "variableId": 1,
                        "variableValid": false,
                        "variableValue": 50
                    },
                    "directionFix": false,
                    "image": {
                        "tileId": 0,
                        "characterName": "イーブル",
                        "direction": 6,
                        "pattern": 1,
                        "characterIndex": 0
                    },
                    "list": [
                        {
                            "code": 231,
                            "indent": 0,
                            "parameters": [
                                21,
                                "イーブル3",
                                0,
                                0,
                                0,
                                0,
                                100,
                                100,
                                0,
                                0
                            ]
                        },
                        {
                            "code": 232,
                            "indent": 0,
                            "parameters": [
                                21,
                                0,
                                0,
                                0,
                                0,
                                0,
                                100,
                                100,
                                255,
                                0,
                                60,
                                true
                            ]
                        },
                        {
                            "code": 101,
                            "indent": 0,
                            "parameters": [
                                "",
                                0,
                                0,
                                2
                            ]
                        },
                        {
                            "code": 401,
                            "indent": 0,
                            "parameters": [
                                "Iburu: \"...Umi.\""
                            ]
                        },
                        {
                            "code": 231,
                            "indent": 0,
                            "parameters": [
                                1,
                                "巫女1",
                                0,
                                0,
                                0,
                                0,
                                100,
                                100,
                                0,
                                0
                            ]
                        },
                        {
                            "code": 232,
                            "indent": 0,
                            "parameters": [
                                1,
                                0,
                                0,
                                0,
                                0,
                                0,
                                100,
                                100,
                                255,
                                0,
                                60,
                                true
                            ]
                        },
                        {
                            "code": 101,
                            "indent": 0,
                            "parameters": [
                                "",
                                0,
                                0,
                                2
                            ]
                        },
                        {
                            "code": 401,
                            "indent": 0,
                            "parameters": [
                                "Umi: \"...\""
                            ]
                        },
                        {
                            "code": 231,
                            "indent": 0,
                            "parameters": [
                                22,
                                "イーブル7",
                                0,
                                0,
                                0,
                                0,
                                100,
                                100,
                                255,
                                0
                            ]
                        },
                        {
                            "code": 101,
                            "indent": 0,
                            "parameters": [
                                "",
                                0,
                                0,
                                2
                            ]
                        },
                        {
                            "code": 401,
                            "indent": 0,
                            "parameters": [
                                "Iburu: \"Are you okay? Let's... have another drink together...\""
                            ]
                        },
                        {
                            "code": 235,
                            "indent": 0,
                            "parameters": [
                                21
                            ]
                        },
                        {
                            "code": 232,
                            "indent": 0,
                            "parameters": [
                                1,
                                0,
                                0,
                                0,
                                0,
                                0,
                                100,
                                100,
                                0,
                                0,
                                30,
                                false
                            ]
                        },
                        {
                            "code": 232,
                            "indent": 0,
                            "parameters": [
                                22,
                                0,
                                0,
                                0,
                                0,
                                0,
                                100,
                                100,
                                0,
                                0,
                                30,
                                true
                            ]
                        },
                        {
                            "code": 235,
                            "indent": 0,
                            "parameters": [
                                1
                            ]
                        },
                        {
                            "code": 235,
                            "indent": 0,
                            "parameters": [
                                22
                            ]
                        },
                        {
                            "code": 356,
                            "indent": 0,
                            "parameters": [
                                "LL_InfoPopupWIndowMV showWindow \\C[2]呪力200　第二の儀式終了　神殺しの酒　が必要 180 300 60 0"
                            ]
                        },
                        {
                            "code": 0,
                            "indent": 0,
                            "parameters": []
                        }
                    ],
                    "moveFrequency": 3,
                    "moveRoute": {
                        "list": [
                            {
                                "code": 0,
                                "parameters": []
                            }
                        ],
                        "repeat": true,
                        "skippable": false,
                        "wait": false
                    },
                    "moveSpeed": 3,
                    "moveType": 0,
                    "priorityType": 1,
                    "stepAnime": false,
                    "through": false,
                    "trigger": 0,
                    "walkAnime": true
                },
                {
                    "conditions": {
                        "actorId": 1,
                        "actorValid": false,
                        "itemId": 156,
                        "itemValid": true,
                        "selfSwitchCh": "A",
                        "selfSwitchValid": false,
                        "switch1Id": 150,
                        "switch1Valid": true,
                        "switch2Id": 156,
                        "switch2Valid": true,
                        "variableId": 1,
                        "variableValid": true,
                        "variableValue": 200
                    },
                    "directionFix": false,
                    "image": {
                        "tileId": 0,
                        "characterName": "イーブル",
                        "direction": 6,
                        "pattern": 1,
                        "characterIndex": 0
                    },
                    "list": [
                        {
                            "code": 101,
                            "indent": 0,
                            "parameters": [
                                "",
                                0,
                                0,
                                2
                            ]
                        },
                        {
                            "code": 401,
                            "indent": 0,
                            "parameters": [
                                "As the event progresses, you will move towards the Iburu ending. It is\nrecommended to save in a separate file."
                            ]
                        },
                        {
                            "code": 101,
                            "indent": 0,
                            "parameters": [
                                "",
                                0,
                                0,
                                2
                            ]
                        },
                        {
                            "code": 401,
                            "indent": 0,
                            "parameters": [
                                "Would you like to save?"
                            ]
                        },
                        {
                            "code": 102,
                            "indent": 0,
                            "parameters": [
                                [
                                    "Yes",
                                    "No"
                                ],
                                1,
                                0,
                                2,
                                0
                            ]
                        },
                        {
                            "code": 402,
                            "indent": 0,
                            "parameters": [
                                0,
                                "はい"
                            ]
                        },
                        {
                            "code": 352,
                            "indent": 1,
                            "parameters": []
                        },
                        {
                            "code": 0,
                            "indent": 1,
                            "parameters": []
                        },
                        {
                            "code": 402,
                            "indent": 0,
                            "parameters": [
                                1,
                                "いいえ"
                            ]
                        },
                        {
                            "code": 0,
                            "indent": 1,
                            "parameters": []
                        },
                        {
                            "code": 404,
                            "indent": 0,
                            "parameters": []
                        },
                        {
                            "code": 231,
                            "indent": 0,
                            "parameters": [
                                21,
                                "イーブル8",
                                0,
                                0,
                                0,
                                0,
                                100,
                                100,
                                0,
                                0
                            ]
                        },
                        {
                            "code": 232,
                            "indent": 0,
                            "parameters": [
                                21,
                                0,
                                0,
                                0,
                                0,
                                0,
                                100,
                                100,
                                255,
                                0,
                                60,
                                true
                            ]
                        },
                        {
                            "code": 101,
                            "indent": 0,
                            "parameters": [
                                "",
                                0,
                                0,
                                2
                            ]
                        },
                        {
                            "code": 401,
                            "indent": 0,
                            "parameters": [
                                "Iburu: \"Umi... you've got some good booze there... care to drink together?\""
                            ]
                        },
                        {
                            "code": 101,
                            "indent": 0,
                            "parameters": [
                                "",
                                0,
                                0,
                                2
                            ]
                        },
                        {
                            "code": 401,
                            "indent": 0,
                            "parameters": [
                                "Will you drink alcohol with Iburu?"
                            ]
                        },
                        {
                            "code": 102,
                            "indent": 0,
                            "parameters": [
                                [
                                    "Yes",
                                    "No"
                                ],
                                1,
                                0,
                                2,
                                0
                            ]
                        },
                        {
                            "code": 402,
                            "indent": 0,
                            "parameters": [
                                0,
                                "はい"
                            ]
                        },
                        {
                            "code": 221,
                            "indent": 1,
                            "parameters": []
                        },
                        {
                            "code": 230,
                            "indent": 1,
                            "parameters": [
                                120
                            ]
                        },
                        {
                            "code": 211,
                            "indent": 1,
                            "parameters": [
                                0
                            ]
                        },
                        {
                            "code": 201,
                            "indent": 1,
                            "parameters": [
                                0,
                                338,
                                5,
                                9,
                                0,
                                2
                            ]
                        },
                        {
                            "code": 235,
                            "indent": 1,
                            "parameters": [
                                21
                            ]
                        },
                        {
                            "code": 222,
                            "indent": 1,
                            "parameters": []
                        },
                        {
                            "code": 0,
                            "indent": 1,
                            "parameters": []
                        },
                        {
                            "code": 402,
                            "indent": 0,
                            "parameters": [
                                1,
                                "いいえ"
                            ]
                        },
                        {
                            "code": 232,
                            "indent": 1,
                            "parameters": [
                                21,
                                0,
                                0,
                                0,
                                0,
                                0,
                                100,
                                100,
                                0,
                                0,
                                30,
                                true
                            ]
                        },
                        {
                            "code": 235,
                            "indent": 1,
                            "parameters": [
                                21
                            ]
                        },
                        {
                            "code": 0,
                            "indent": 1,
                            "parameters": []
                        },
                        {
                            "code": 404,
                            "indent": 0,
                            "parameters": []
                        },
                        {
                            "code": 0,
                            "indent": 0,
                            "parameters": []
                        }
                    ],
                    "moveFrequency": 3,
                    "moveRoute": {
                        "list": [
                            {
                                "code": 0,
                                "parameters": []
                            }
                        ],
                        "repeat": true,
                        "skippable": false,
                        "wait": false
                    },
                    "moveSpeed": 3,
                    "moveType": 0,
                    "priorityType": 1,
                    "stepAnime": false,
                    "through": false,
                    "trigger": 0,
                    "walkAnime": true
                },
                {
                    "conditions": {
                        "actorId": 1,
                        "actorValid": false,
                        "itemId": 1,
                        "itemValid": false,
                        "selfSwitchCh": "A",
                        "selfSwitchValid": false,
                        "switch1Id": 152,
                        "switch1Valid": true,
                        "switch2Id": 1,
                        "switch2Valid": false,
                        "variableId": 1,
                        "variableValid": false,
                        "variableValue": 0
                    },
                    "directionFix": false,
                    "image": {
                        "tileId": 0,
                        "characterName": "イーブル",
                        "direction": 6,
                        "pattern": 1,
                        "characterIndex": 0
                    },
                    "list": [
                        {
                            "code": 231,
                            "indent": 0,
                            "parameters": [
                                21,
                                "イーブル3",
                                0,
                                0,
                                0,
                                0,
                                100,
                                100,
                                0,
                                0
                            ]
                        },
                        {
                            "code": 232,
                            "indent": 0,
                            "parameters": [
                                21,
                                0,
                                0,
                                0,
                                0,
                                0,
                                100,
                                100,
                                255,
                                0,
                                60,
                                true
                            ]
                        },
                        {
                            "code": 101,
                            "indent": 0,
                            "parameters": [
                                "",
                                0,
                                0,
                                2
                            ]
                        },
                        {
                            "code": 401,
                            "indent": 0,
                            "parameters": [
                                "Iburu: \"...Umi.\""
                            ]
                        },
                        {
                            "code": 231,
                            "indent": 0,
                            "parameters": [
                                1,
                                "巫女1",
                                0,
                                0,
                                0,
                                0,
                                100,
                                100,
                                0,
                                0
                            ]
                        },
                        {
                            "code": 232,
                            "indent": 0,
                            "parameters": [
                                1,
                                0,
                                0,
                                0,
                                0,
                                0,
                                100,
                                100,
                                255,
                                0,
                                60,
                                true
                            ]
                        },
                        {
                            "code": 101,
                            "indent": 0,
                            "parameters": [
                                "",
                                0,
                                0,
                                2
                            ]
                        },
                        {
                            "code": 401,
                            "indent": 0,
                            "parameters": [
                                "Umi: \"...\""
                            ]
                        },
                        {
                            "code": 231,
                            "indent": 0,
                            "parameters": [
                                22,
                                "イーブル7",
                                0,
                                0,
                                0,
                                0,
                                100,
                                100,
                                255,
                                0
                            ]
                        },
                        {
                            "code": 101,
                            "indent": 0,
                            "parameters": [
                                "",
                                0,
                                0,
                                2
                            ]
                        },
                        {
                            "code": 401,
                            "indent": 0,
                            "parameters": [
                                "Iburu: \"If you're going through a tough time, bring some liquor... Let's\ndrink together...\""
                            ]
                        },
                        {
                            "code": 235,
                            "indent": 0,
                            "parameters": [
                                21
                            ]
                        },
                        {
                            "code": 232,
                            "indent": 0,
                            "parameters": [
                                1,
                                0,
                                0,
                                0,
                                0,
                                0,
                                100,
                                100,
                                0,
                                0,
                                30,
                                false
                            ]
                        },
                        {
                            "code": 232,
                            "indent": 0,
                            "parameters": [
                                22,
                                0,
                                0,
                                0,
                                0,
                                0,
                                100,
                                100,
                                0,
                                0,
                                30,
                                true
                            ]
                        },
                        {
                            "code": 235,
                            "indent": 0,
                            "parameters": [
                                1
                            ]
                        },
                        {
                            "code": 235,
                            "indent": 0,
                            "parameters": [
                                22
                            ]
                        },
                        {
                            "code": 0,
                            "indent": 0,
                            "parameters": []
                        }
                    ],
                    "moveFrequency": 3,
                    "moveRoute": {
                        "list": [
                            {
                                "code": 0,
                                "parameters": []
                            }
                        ],
                        "repeat": true,
                        "skippable": false,
                        "wait": false
                    },
                    "moveSpeed": 3,
                    "moveType": 0,
                    "priorityType": 1,
                    "stepAnime": false,
                    "through": false,
                    "trigger": 0,
                    "walkAnime": true
                }
            ],
            "x": 4,
            "y": 8
        },
        null,
        null
    ]
}